napcat/__init__.py
napcat/client.py
napcat/client_api.py
napcat/connection.py
napcat/py.typed
napcat/server.py
napcat/types/__init__.py
napcat/types/events/__init__.py
napcat/types/events/base.py
napcat/types/events/message.py
napcat/types/events/meta.py
napcat/types/events/notice/BotOfflineEvent.py
napcat/types/events/notice/FriendAddNoticeEvent.py
napcat/types/events/notice/FriendRecallNoticeEvent.py
napcat/types/events/notice/GroupAdminNoticeEvent.py
napcat/types/events/notice/GroupBanEvent.py
napcat/types/events/notice/GroupCardEvent.py
napcat/types/events/notice/GroupDecreaseEvent.py
napcat/types/events/notice/GroupEssenceEvent.py
napcat/types/events/notice/GroupGrayTipEvent.py
napcat/types/events/notice/GroupIncreaseEvent.py
napcat/types/events/notice/GroupNameEvent.py
napcat/types/events/notice/GroupNoticeEvent.py
napcat/types/events/notice/GroupRecallNoticeEvent.py
napcat/types/events/notice/GroupTitleEvent.py
napcat/types/events/notice/GroupUploadNoticeEvent.py
napcat/types/events/notice/InputStatusEvent.py
napcat/types/events/notice/MsgEmojiLikeEvent.py
napcat/types/events/notice/OnlineFileNoticeEvent.py
napcat/types/events/notice/OnlineFileReceiveEvent.py
napcat/types/events/notice/OnlineFileSendEvent.py
napcat/types/events/notice/PokeEvent.py
napcat/types/events/notice/ProfileLikeEvent.py
napcat/types/events/notice/__init__.py
napcat/types/events/notice/base.py
napcat/types/events/request.py
napcat/types/messages/__init__.py
napcat/types/messages/base.py
napcat/types/messages/generated.py
napcat/types/schemas.py
napcat/types/utils.py
napcat_sdk-0.3.4.dist-info/WHEEL
napcat_sdk-0.3.4.dist-info/METADATA
napcat_sdk-0.3.4.dist-info/RECORD
