Metadata-Version: 2.3
Name: napcat-sdk
Version: 0.3.4
Summary: NapCat SDK for Python - Fully typed and async ready
Keywords: napcat,sdk,api,async,typed
Author: 吴天一
Author-email: 吴天一 <faithleysath@gmail.com>
License: MIT License
Classifier: Development Status :: 3 - Alpha
Classifier: Intended Audience :: Developers
Classifier: License :: OSI Approved :: MIT License
Classifier: Programming Language :: Python :: 3.12
Classifier: Programming Language :: Python :: 3.13
Classifier: Programming Language :: Python :: 3.14
Classifier: Operating System :: OS Independent
Classifier: Typing :: Typed
Classifier: Topic :: Software Development :: Libraries :: Python Modules
Classifier: Topic :: Communications :: Chat
Requires-Dist: orjson>=3.11.5
Requires-Dist: websockets>=15.0.1
Requires-Python: >=3.12
Project-URL: Homepage, https://github.com/faithleysath/napcat-sdk
Project-URL: Repository, https://github.com/faithleysath/napcat-sdk
Project-URL: Documentation, https://github.com/faithleysath/napcat-sdk/blob/main/README.md
Project-URL: Bug Tracker, https://github.com/faithleysath/napcat-sdk/issues
